django_scrapyd_manager/__init__.py
django_scrapyd_manager/admin.py
django_scrapyd_manager/apps.py
django_scrapyd_manager/cache.py
django_scrapyd_manager/forms.py
django_scrapyd_manager/guardian.py
django_scrapyd_manager/models.py
django_scrapyd_manager/scrapyd_api.py
django_scrapyd_manager/signals.py
django_scrapyd_manager/tests.py
django_scrapyd_manager/utils.py
django_scrapyd_manager/migrations/0001_initial.py
django_scrapyd_manager/migrations/0002_spidergroup_code.py
django_scrapyd_manager/migrations/0003_delete_guardianlock_alter_guardian_create_time_and_more.py
django_scrapyd_manager/migrations/0004_alter_guardianlog_node_alter_guardianlog_spider_and_more.py
django_scrapyd_manager/migrations/__init__.py
django_scrapyd_manager/static/admin/js/spider_group_linked.js
django_scrapyd_manager-0.2.3.dist-info/licenses/LICENSE
django_scrapyd_manager-0.2.3.dist-info/METADATA
django_scrapyd_manager-0.2.3.dist-info/WHEEL
django_scrapyd_manager-0.2.3.dist-info/top_level.txt
django_scrapyd_manager-0.2.3.dist-info/RECORD
