Metadata-Version: 2.4
Name: django-scrapyd-manager
Version: 0.2.3
Summary: A Django application for managing Scrapyd nodes, projects, spiders and jobs
Author-email: Cone387 <1183008540@qq.com>
License-Expression: MIT
Project-URL: Homepage, https://github.com/cone387/DjangoScrapydManager
Project-URL: Repository, https://github.com/cone387/DjangoScrapydManager
Keywords: django,scrapyd,scrapy,web-scraping,manager
Classifier: Development Status :: 3 - Alpha
Classifier: Environment :: Web Environment
Classifier: Framework :: Django
Classifier: Framework :: Django :: 5.2
Classifier: Intended Audience :: Developers
Classifier: Operating System :: OS Independent
Classifier: Programming Language :: Python
Classifier: Programming Language :: Python :: 3
Classifier: Programming Language :: Python :: 3.13
Classifier: Topic :: Internet :: WWW/HTTP
Classifier: Topic :: Software Development :: Libraries :: Python Modules
Requires-Python: >=3.13
License-File: LICENSE
Requires-Dist: django>=5.2.5
Requires-Dist: requests>=2.32.4
Requires-Dist: django-sched>=0.1.3
Dynamic: license-file
